test/__init__.py
test/test_test.py
walletthon/__init__.py
walletthon/types.py
walletthon-0.0.1.dist-info/METADATA
walletthon-0.0.1.dist-info/WHEEL
walletthon-0.0.1.dist-info/top_level.txt
walletthon-0.0.1.dist-info/RECORD
